SendSingleW10/Funciones.py
SendSingleW10/__init__.py
SendSingleW10-0.0.4.dist-info/METADATA
SendSingleW10-0.0.4.dist-info/WHEEL
SendSingleW10-0.0.4.dist-info/top_level.txt
SendSingleW10-0.0.4.dist-info/RECORD
