Metadata-Version: 2.1
Name: SendSingleW10
Version: 0.0.4
Summary: Librería para Enviar data a un servidor en base a Librerias de Windows 10
Home-page: https://github.com/AHernanandez1234/
Author: Arturo Hernandez
Author-email: ahernandez1980ene@gmail.com
License: MIT
Requires-Dist: CheckVersionW10
